{
    "editionTitle": "Women Talking, Women Thinking",
    "editionSubtitle": "",
    "ignoreNamespace": true,
    "documents": "//div[@type='essay'or@type='biography']",
    "documentContent": "",
    "documentTitle": "head",
    "documentAuthor": "",
    "indexDocument": "//div[@type='index']",
    "documentImages": "",
    "documentNotes": "",
    "documentLinks": "",
    "inputs": [
        "https://raw.githubusercontent.com/djakacki/heresies/main/issue04/text/women_talking.xml"
    ],
    "curation": {
        "markup": [
            {
                "xpath": "//div",
                "label": "div"
            },
            {
                "xpath": "//persName",
                "label": "people"
            },
            {
                "xpath": "//title",
                "label": "works"
            }
        ],
        "toc": [
            "8bb7a9a7371e1c529a82bb414b28da1ad19a5a33bb6983d3bbdc6789f9a3d52d",
            "3c528a1cf8aca16fe3d7b22f43ed9adc77495e6f8870a78af77dc5367156ab93"
        ]
    }
}